type_aliases/__init__.py
type_aliases/py.typed
type_aliases-0.0.6.dist-info/METADATA
type_aliases-0.0.6.dist-info/WHEEL
type_aliases-0.0.6.dist-info/RECORD
